orkestra/__init__.py
orkestra/core/__init__.py
orkestra/core/agent.py
orkestra/core/llm/orkestra_openai.py
orkestra/core/llm/orkestra_standard_llm.py
orkestra/core/llm_abstraction.py
orkestra/core/workflow.py
orkestra/orkestra.py
orkestra/server.py
orkestra_sdk-0.0.3.dist-info/LICENSE
orkestra_sdk-0.0.3.dist-info/METADATA
orkestra_sdk-0.0.3.dist-info/WHEEL
orkestra_sdk-0.0.3.dist-info/RECORD
