Metadata-Version: 2.3
Name: orkestra-sdk
Version: 0.0.3
Summary: The Python SDK for Orkestra, a powerful platform for building, deploying, and managing AI-native workflows and agents.
Author: Orkestra Labs
Author-email: hello@orkestration.com
Requires-Python: >=3.9,<4.0
Classifier: Programming Language :: Python :: 3
Classifier: Programming Language :: Python :: 3.9
Classifier: Programming Language :: Python :: 3.10
Classifier: Programming Language :: Python :: 3.11
Classifier: Programming Language :: Python :: 3.12
Classifier: Programming Language :: Python :: 3.13
Requires-Dist: fastapi (>=0.111.0,<0.112.0)
Requires-Dist: openai (>=1.35.13,<2.0.0)
Requires-Dist: pinecone-client (>=4.1.2,<5.0.0)
Requires-Dist: pydantic (>=2.8.2,<3.0.0)
Requires-Dist: uvicorn (>=0.30.1,<0.31.0)
Project-URL: Bug Tracker, https://github.com/your-username/orkestra_sdk/issues
Project-URL: Documentation, https://docs.orkestration.com
Project-URL: Homepage, https://orkestration.com
